{
    "nav-exchange": "",
    "nav-education": "",
    "nav-interview": "",
    "nav-gallery": "",
    "nav-contact": "",
    "exchange-hero-title": "",
    "exchange-hero-subtitle": "",
    "event-202401-title": "",
    "event-202401-details": "",
    "event-202401-thought": "",
    "event-202405-title": "",
    "event-202405-details": "",
    "event-202405-thought": "",
    "event-202501-title": "",
    "event-202501-details": "",
    "event-202501-thought": "",
    "event-202509-title": "",
    "event-202509-details": "",
    "event-202509-thought": "",
    "event-202511-title": "",
    "event-202511-details": "",
    "event-202511-thought": "",
    "event-202512-title": "",
    "event-202512-details": "",
    "event-202512-thought": "",
    "event-202601-title": "",
    "event-202601-details": "",
    "event-202601-thought": "",
    "edu-hero-title": "",
    "edu-hero-subtitle": "",
    "edu-card1-title": "",
    "edu-card1-content": "",
    "edu-card2-title": "",
    "edu-card2-content": "",
    "edu-card3-title": "",
    "edu-card3-content": "",
    "interview-hero-title": "",
    "interview-hero-subtitle": "",
    "gallery-hero-title": "",
    "gallery-hero-subtitle": "",
    "contact-hero-title": "",
    "contact-hero-subtitle": "",
    "contact-info-title": "",
    "contact-credits-title": "",
    "contact-faq-title": ""
  }